xia_composer/__init__.py
xia_composer/campaign.cpython-310-darwin.so
xia_composer/dialog.cpython-310-darwin.so
xia_composer/knowledge.cpython-310-darwin.so
xia_composer/mission.cpython-310-darwin.so
xia_composer/parser.cpython-310-darwin.so
xia_composer/pattern.cpython-310-darwin.so
xia_composer/target.cpython-310-darwin.so
xia_composer/task.cpython-310-darwin.so
xia_composer/template.cpython-310-darwin.so
xia_composer/validation.cpython-310-darwin.so
xia_composer/templates/campaigns/start_up.json
xia_composer/templates/missions/meeting_organization.json
xia_composer/templates/prompts/mission.prompt
xia_composer/templates/reviews/process_review.json
xia_composer/templates/skills/general/general.bio
xia_composer/templates/skills/software/project_manager.bio
xia_composer/templates/tasks/fix/error_locating.prompt
xia_composer/templates/tasks/requirements/meeting_logo.prompt
xia_composer/templates/tasks/requirements/meeting_objectives_analysis.prompt
xia_composer/templates/tasks/reviews/bug_detected.prompt
xia_composer/templates/tasks/reviews/potential_issue_detected.prompt
xia_composer/templates/tasks/reviews/review_passed.prompt
xia_composer-0.1.3.dist-info/LICENSE.txt
xia_composer-0.1.3.dist-info/METADATA
xia_composer-0.1.3.dist-info/WHEEL
xia_composer-0.1.3.dist-info/top_level.txt
xia_composer-0.1.3.dist-info/RECORD
