Metadata-Version: 2.1
Name: xia-composer
Version: 0.1.3
Summary: UNKNOWN
Home-page: https://develop.x-i-a.com/docs/xia-composer/0.1.3/index.html
Author: X-I-A
Author-email: admin@x-i-a.com
License: UNKNOWN
Platform: UNKNOWN
Requires-Python: >=3.9
License-File: LICENSE.txt
Requires-Dist: jinja2
Requires-Dist: requests
Requires-Dist: xia-engine
Requires-Dist: xia-diff-match-patch
